{
  "template": "method",
  "related": [],
  "scratchblock": "change pen [size v] by ()",
  "name": "changeSize()",
  "class": "Pen",
  "description": "Verändert die Größe des Stifts um den übergebenen Wert.",
  "syntax": [".changeSize(amount)"],
  "returns": "void",
  "examples": [
    {
      "src": "PenChangeSize.java",
      "preview": "PenChangeSize.gif",
      "lines": "reg:[Rr]ecorder"
    }
  ],
  "parameters": [
    {
      "name": "amount",
      "description": "Wert um den die Größe verändert werden soll",
      "type": "float"
    }
  ]
}
